pyrao/__init__.py
pyrao/analysis/__init__.py
pyrao/integration/__init__.py
pyrao/integration/bsadata.py
pyrao/integration/cinterp1d.cp37-win_amd64.pyd
pyrao/integration/cinterp1d.py
pyrao/integration/coords.py
pyrao/integration/sigproc.py
pyrao-0.9.dist-info/METADATA
pyrao-0.9.dist-info/RECORD
pyrao-0.9.dist-info/WHEEL
pyrao-0.9.dist-info/top_level.txt
